[
    {
        "config-name": "R 3.5 on Windows",
        "os": "windows-latest",
        "r": "3.5",
        "runOnEvent": ["pull_request"]
    },
    {
        "config-name": "R 3.5 on macOS",
        "os": "macOS-latest",
        "r": "3.5",
        "runOnEvent": []
    },
    {
        "config-name": "R 3.5 on Ubuntu",
        "os": "ubuntu-20.04",
        "r": "3.5",
        "runOnEvent": ["pull_request","push"]
    },
    {
        "config-name": "R release version on Ubuntu",
        "os": "ubuntu-20.04",
        "r": "release",
        "runOnEvent": ["pull_request","push"]
    },
    {
        "config-name": "R devel version on Ubuntu",
        "os": "ubuntu-20.04",
        "r": "devel",
        "runOnEvent": ["pull_request","push"]
    }
]
